{
    "$schema": "https://schema.management.azure.com/schemas/2019-04-01/deploymentTemplate.json#",
    "contentVersion": "1.0.0.0",
    "parameters": {
        "virtualNetworks_MyVnet_name": {
            "defaultValue": "MyVnet1",
            "type": "String"
        }
    },
    "variables": {},
    "resources": [
        {
            "type": "Microsoft.Network/virtualNetworks",
            "apiVersion": "2023-06-01",
            "name": "[parameters('virtualNetworks_MyVnet_name')]",
            "location": "southindia",
            "properties": {
                "addressSpace": {
                    "addressPrefixes": [
                        "10.0.0.0/16"
                    ]#comments added here
                    
                },
                "subnets": [
                    {
                        "name": "MySubnet1",
                        "id": "[resourceId('Microsoft.Network/virtualNetworks/subnets', parameters('virtualNetworks_MyVnet_name'), 'MySubnet')]",
                        "properties": {
                            "addressPrefix": "10.0.0.0/24",
                            "delegations": [],
                            "privateEndpointNetworkPolicies": "Disabled",
                            "privateLinkServiceNetworkPolicies": "Enabled"
                        },
                        "type": "Microsoft.Network/virtualNetworks/subnets"
                    }
                ],
                "virtualNetworkPeerings": [],
                "enableDdosProtection": false
            }
        },
        {
            "type": "Microsoft.Network/virtualNetworks/subnets",
            "apiVersion": "2023-06-01",
            "name": "[concat(parameters('virtualNetworks_MyVnet_name'), '/MySubnet')]",
            "dependsOn": [
                "[resourceId('Microsoft.Network/virtualNetworks', parameters('virtualNetworks_MyVnet_name'))]"
            ],
            "properties": {
                "addressPrefix": "10.0.0.0/24",
                "delegations": [],
                "privateEndpointNetworkPolicies": "Disabled",
                "privateLinkServiceNetworkPolicies": "Enabled"
            }
        }
    ]
}